{
  "projectId": "imagined-tracker-t3bk6",
  "appId": "1:244974590290:web:d223f6283658b41d75028b",
  "apiKey": "AIzaSyCrgqLkgiHbglG-qc7RsMFro67QSxq_9Zs",
  "authDomain": "imagined-tracker-t3bk6.firebaseapp.com",
  "firestoreDatabaseId": "ai-studio-ailinkedingrowth-f1577716-3b73-4452-a597-0937d62fe36f",
  "storageBucket": "imagined-tracker-t3bk6.firebasestorage.app",
  "messagingSenderId": "244974590290",
  "measurementId": "",
  "oAuthClientId": "244974590290-75gkhq4063h19k4lf43nds4ul5n7mbfe.apps.googleusercontent.com"
}